sanic_mysql/__init__.py
sanic_mysql/mysql.py
sanic_aiomysql-2022.4.17.dist-info/LICENSE
sanic_aiomysql-2022.4.17.dist-info/METADATA
sanic_aiomysql-2022.4.17.dist-info/WHEEL
sanic_aiomysql-2022.4.17.dist-info/top_level.txt
sanic_aiomysql-2022.4.17.dist-info/RECORD
