Metadata-Version: 2.1
Name: sanic-aiomysql
Version: 2022.4.17
Summary: Easy to use MySQL for sanic.
Home-page: https://github.com/tuna2134/sanic-aioMySQL
Author: DMS
Author-email: masato190411@gmail.com
License: UNKNOWN
Platform: UNKNOWN
Classifier: Programming Language :: Python :: 3.8
Classifier: License :: OSI Approved :: MIT License
Classifier: Operating System :: OS Independent
License-File: LICENSE
Requires-Dist: aiomysql (>=0.1.0)
